intramove/__init__.py
intramove/intramove.py
intramove-0.0.15.dist-info/LICENSE
intramove-0.0.15.dist-info/METADATA
intramove-0.0.15.dist-info/WHEEL
intramove-0.0.15.dist-info/top_level.txt
intramove-0.0.15.dist-info/RECORD
