Metadata-Version: 2.1
Name: intramove
Version: 0.0.15
Summary: A client for interacting with Intramove.ai API
Home-page: https://github.com/abdelatifsd/intramove
Author: Abdellatif Dalab
Author-email: abdulatifsal@gmail.com
License: UNKNOWN
Keywords: python,deep learning,finance,text classification,text analysis,sentiment
Platform: UNKNOWN
Classifier: Programming Language :: Python :: 3
Classifier: License :: OSI Approved :: MIT License
Classifier: Operating System :: OS Independent
Requires-Python: >=3.6
License-File: LICENSE
Requires-Dist: ratelimiter
Requires-Dist: bson
Requires-Dist: requests
